keepassfunctions/__init__.py
keepassfunctions/keepassfunctions.py
keepassfunctions-2.0.dist-info/METADATA
keepassfunctions-2.0.dist-info/WHEEL
keepassfunctions-2.0.dist-info/top_level.txt
keepassfunctions-2.0.dist-info/RECORD
